lnd_grpc/__init__.py
lnd_grpc/base_client.py
lnd_grpc/config.py
lnd_grpc/invoices.py
lnd_grpc/lightning.py
lnd_grpc/lnd_grpc.py
lnd_grpc/utilities.py
lnd_grpc/wallet_unlocker.py
lnd_grpc/protos/__init__.py
lnd_grpc/protos/download_proto_files.py
lnd_grpc/protos/generate_protoc.py
lnd_grpc/protos/invoices_pb2.py
lnd_grpc/protos/invoices_pb2_grpc.py
lnd_grpc/protos/rpc_pb2.py
lnd_grpc/protos/rpc_pb2_grpc.py
loop_rpc/__init__.py
loop_rpc/loop_rpc.py
loop_rpc/protos/__init__.py
loop_rpc/protos/loop_client_pb2.py
loop_rpc/protos/loop_client_pb2_grpc.py
lnd_grpc-0.4.0.dist-info/LICENSE
lnd_grpc-0.4.0.dist-info/METADATA
lnd_grpc-0.4.0.dist-info/WHEEL
lnd_grpc-0.4.0.dist-info/top_level.txt
lnd_grpc-0.4.0.dist-info/RECORD
