Metadata-Version: 2.1
Name: lnd-grpc
Version: 0.4.0
Summary: An LND gRPC client for Python 3.6
Home-page: https://github.com/willcl-ark/lnd_grpc
Author: Will Clark
Author-email: will8clark@gmail.com
License: UNKNOWN
Keywords: lnd grpc
Platform: UNKNOWN
Classifier: Programming Language :: Python :: 3.6
Classifier: License :: OSI Approved :: MIT License
Classifier: Operating System :: OS Independent
Requires-Python: >=3.6
